pretix_postfinance/__init__.py
pretix_postfinance/_types.py
pretix_postfinance/api.py
pretix_postfinance/apps.py
pretix_postfinance/payment.py
pretix_postfinance/py.typed
pretix_postfinance/signals.py
pretix_postfinance/urls.py
pretix_postfinance/views.py
pretix_postfinance/static/pretix_postfinance/pf_logo.svg
pretix_postfinance/static/pretix_postfinance/pretix-postfinance.js
pretix_postfinance/templates/pretixplugins/postfinance/checkout_payment_confirm.html
pretix_postfinance/templates/pretixplugins/postfinance/control.html
pretix_postfinance/templates/pretixplugins/postfinance/control_head.html
pretix_postfinance/templates/pretixplugins/postfinance/control_settings.html
pretix_postfinance/templates/pretixplugins/postfinance/pending.html
pretix_postfinance-1.2.0.dist-info/licenses/LICENSE
pretix_postfinance-1.2.0.dist-info/METADATA
pretix_postfinance-1.2.0.dist-info/WHEEL
pretix_postfinance-1.2.0.dist-info/entry_points.txt
pretix_postfinance-1.2.0.dist-info/top_level.txt
pretix_postfinance-1.2.0.dist-info/RECORD
