Metadata-Version: 2.4
Name: pretix-postfinance
Version: 1.2.0
Summary: PostFinance Checkout payment plugin for pretix
Author-email: Sweenu <contact@sweenu.xyz>
Maintainer-email: Sweenu <contact@sweenu.xyz>
License-Expression: AGPL-3.0-or-later
Project-URL: Homepage, https://github.com/sweenu/pretix-postfinance
Project-URL: Repository, https://github.com/sweenu/pretix-postfinance
Keywords: pretix,payment,postfinance,checkout
Classifier: Development Status :: 4 - Beta
Classifier: Framework :: Django
Classifier: Intended Audience :: Developers
Classifier: Operating System :: OS Independent
Classifier: Programming Language :: Python :: 3
Classifier: Programming Language :: Python :: 3.9
Classifier: Programming Language :: Python :: 3.10
Classifier: Programming Language :: Python :: 3.11
Classifier: Programming Language :: Python :: 3.12
Requires-Python: <3.13,>=3.9
License-File: LICENSE
Requires-Dist: postfinancecheckout>=6.0.0
Provides-Extra: dev
Requires-Dist: pytest>=7.0; extra == "dev"
Requires-Dist: pytest-cov>=4.0; extra == "dev"
Requires-Dist: pytest-django>=4.0; extra == "dev"
Requires-Dist: pretix>=2025.10; extra == "dev"
Requires-Dist: mypy<1.15,>=1.0; extra == "dev"
Requires-Dist: django-stubs<5.1,>=4.0; extra == "dev"
Requires-Dist: ruff>=0.1; extra == "dev"
Requires-Dist: commitizen>=4.9.1; extra == "dev"
Dynamic: license-file
